echoloader/__init__.py
echoloader/__main__.py
echoloader/config.py
echoloader/dimse/__init__.py
echoloader/dimse/dimse.py
echoloader/dimse/fs.py
echoloader/dimse/store.py
echoloader/dimse/tls.py
echoloader/lib/hl7.py
echoloader/login.py
echoloader/qt.py
echoloader/results_sync/__init__.py
echoloader/results_sync/hl7_sync.py
echoloader/results_sync/pdf_sc.py
echoloader/sync.py
echoloader/watcher.py
echoloader-2.1.0.2.dist-info/entry_points.txt
echoloader-2.1.0.2.dist-info/METADATA
echoloader-2.1.0.2.dist-info/WHEEL
echoloader-2.1.0.2.dist-info/RECORD
