Metadata-Version: 2.1
Name: echoloader
Version: 2.1.0.2
Summary: 
Author: mathias
Author-email: mathias@us2.ai
Requires-Python: >=3.11,<3.12
Classifier: Programming Language :: Python :: 3
Classifier: Programming Language :: Python :: 3.11
Requires-Dist: av (==10.0.0)
Requires-Dist: boto3 (>=1.34.63,<2.0.0)
Requires-Dist: hl7apy (>=1.3.4,<2.0.0)
Requires-Dist: imageio (==2.31.4)
Requires-Dist: imageio-ffmpeg (==0.4.9)
Requires-Dist: numpy (==1.23.5)
Requires-Dist: opencv-python-headless (>=4.5.5.64,<5.0.0.0)
Requires-Dist: pathy (>=0.10.2,<0.11.0)
Requires-Dist: pydicom (>=2.3.0,<3.0.0)
Requires-Dist: pymupdf (>=1.24.2,<2.0.0)
Requires-Dist: pynetdicom (>=2.0.2,<3.0.0)
Requires-Dist: pysftp (>=0.2.9,<0.3.0)
Requires-Dist: python-dateutil (>=2.8.2,<3.0.0)
Requires-Dist: python-gdcm (>=3.0.12,<4.0.0)
Requires-Dist: requests (>=2.27.1,<3.0.0)
Requires-Dist: tqdm (>=4.64.0,<5.0.0)
Requires-Dist: watchdog (>=2.1.7,<3.0.0)
